odoo/addons/beesdoo_crelan_csv/README.rst
odoo/addons/beesdoo_crelan_csv/__init__.py
odoo/addons/beesdoo_crelan_csv/__manifest__.py
odoo/addons/beesdoo_crelan_csv/i18n/fr_BE.po
odoo/addons/beesdoo_crelan_csv/models/__init__.py
odoo/addons/beesdoo_crelan_csv/models/account_journal.py
odoo/addons/beesdoo_crelan_csv/readme/CONTRIBUTORS.rst
odoo/addons/beesdoo_crelan_csv/readme/DESCRIPTION.rst
odoo/addons/beesdoo_crelan_csv/static/description/index.html
odoo/addons/beesdoo_crelan_csv/wizard/__init__.py
odoo/addons/beesdoo_crelan_csv/wizard/import_crelan_csv.py
odoo12_addon_beesdoo_crelan_csv-12.0.1.0.0.99.dev4.dist-info/METADATA
odoo12_addon_beesdoo_crelan_csv-12.0.1.0.0.99.dev4.dist-info/WHEEL
odoo12_addon_beesdoo_crelan_csv-12.0.1.0.0.99.dev4.dist-info/top_level.txt
odoo12_addon_beesdoo_crelan_csv-12.0.1.0.0.99.dev4.dist-info/RECORD
